[{"animeRomajiName":"Leadale no Daichi nite","animeEnglishName":"In the Land of Leadale","altAnimeNames":["Leadale no Daichi nite","In the Land of Leadale"],"altAnimeNamesAnswers":[],"songArtist":"TRUE","songName":"Happy encount","songType":1,"songTypeNumber":1,"songDifficulty":40,"animeType":"TV","animeVintage":"Winter 2022","annId":24106,"malId":48239,"kitsuId":44186,"aniListId":130166,"animeTags":[],"animeGenre":[],"rebroadcast":0,"dub":0,"startPoint":null,"audio":"48fwuj.mp3","video480":null,"video720":"g4x4nu.webm","correctGuess":true,"incorrectGuess":true},{"animeRomajiName":"Orient","animeEnglishName":"Orient","altAnimeNames":["Orient","Orient"],"altAnimeNamesAnswers":[],"songArtist":"Da-iCE","songName":"Break out","songType":1,"songTypeNumber":1,"songDifficulty":30,"animeType":"TV","animeVintage":"Winter 2022","annId":24572,"malId":45560,"kitsuId":44205,"aniListId":128034,"animeTags":[],"animeGenre":[],"rebroadcast":0,"dub":0,"startPoint":null,"audio":"rg4q8j.mp3","video480":null,"video720":"geju2x.webm","correctGuess":true,"incorrectGuess":true},{"animeRomajiName":"Hakozume: Kouban Joshi no Gyakushuu","animeEnglishName":"Police in a Pod","altAnimeNames":["Hakozume: Kouban Joshi no Gyakushuu","Police in a Pod"],"altAnimeNamesAnswers":[],"songArtist":"Riko Azuna","songName":"Shiranakya","songType":1,"songTypeNumber":1,"songDifficulty":27,"animeType":"TV","animeVintage":"Winter 2022","annId":24595,"malId":49519,"kitsuId":null,"aniListId":137312,"animeTags":[],"animeGenre":[],"rebroadcast":0,"dub":0,"startPoint":null,"audio":"2ato8o.mp3","video480":null,"video720":"k2sami.webm","correctGuess":true,"incorrectGuess":true},{"animeRomajiName":"Tokyo 24-ku","animeEnglishName":"Tokyo 24th Ward","altAnimeNames":["Tokyo 24-ku","Tokyo 24th Ward"],"altAnimeNamesAnswers":[],"songArtist":"Survive Said The Prophet","songName":"Papersky","songType":1,"songTypeNumber":1,"songDifficulty":28,"animeType":"TV","animeVintage":"Winter 2022","annId":24898,"malId":50204,"kitsuId":null,"aniListId":140643,"animeTags":[],"animeGenre":[],"rebroadcast":0,"dub":0,"startPoint":null,"audio":"yd6l32.mp3","video480":null,"video720":"ddokb4.webm","correctGuess":true,"incorrectGuess":true},{"animeRomajiName":"Dolls' Frontline","animeEnglishName":"Girls' Frontline","altAnimeNames":["Dolls' Frontline","Girls' Frontline"],"altAnimeNamesAnswers":[],"songArtist":"yukaDD(;´∀｀)","songName":"BAD CANDY","songType":1,"songTypeNumber":1,"songDifficulty":35,"animeType":"TV","animeVintage":"Winter 2022","annId":23960,"malId":46604,"kitsuId":43929,"aniListId":128828,"animeTags":[],"animeGenre":[],"rebroadcast":0,"dub":0,"startPoint":null,"audio":"w3rutt.mp3","video480":null,"video720":"v7wm2h.webm","correctGuess":true,"incorrectGuess":true},{"animeRomajiName":"Akebi-chan no Sailor Fuku","animeEnglishName":"Akebi's Sailor Uniform","altAnimeNames":["Akebi-chan no Sailor Fuku","Akebi's Sailor Uniform"],"altAnimeNamesAnswers":[],"songArtist":"Roubai Gakuen Chuutoubu 1-nen 3-kumi","songName":"Hajimari no Setsuna","songType":1,"songTypeNumber":1,"songDifficulty":39,"animeType":"TV","animeVintage":"Winter 2022","annId":24189,"malId":48553,"kitsuId":44210,"aniListId":131548,"animeTags":[],"animeGenre":[],"rebroadcast":0,"dub":0,"startPoint":null,"audio":"s5ygg1.mp3","video480":null,"video720":"rknfhf.webm","correctGuess":true,"incorrectGuess":true},{"animeRomajiName":"Sono Bisque Doll wa Koi o Suru","animeEnglishName":"My Dress-Up Darling","altAnimeNames":["Sono Bisque Doll wa Koi o Suru","My Dress-Up Darling"],"altAnimeNamesAnswers":[],"songArtist":"Spira Spica","songName":"Sunsun Days","songType":1,"songTypeNumber":1,"songDifficulty":60,"animeType":"TV","animeVintage":"Winter 2022","annId":24306,"malId":48736,"kitsuId":44382,"aniListId":132405,"animeTags":[],"animeGenre":[],"rebroadcast":0,"dub":0,"startPoint":null,"audio":"zmswti.mp3","video480":"5s3b8i.webm","video720":"j5nu6u.webm","correctGuess":true,"incorrectGuess":true},{"animeRomajiName":"Saiyuki Reload: Zeroin","animeEnglishName":"Saiyuki Reload: Zeroin","altAnimeNames":["Saiyuki Reload: Zeroin","Saiyuki Reload: Zeroin"],"altAnimeNamesAnswers":[],"songArtist":"GRANRODEO","songName":"Kami mo Hotoke mo","songType":1,"songTypeNumber":1,"songDifficulty":21,"animeType":"TV","animeVintage":"Winter 2022","annId":24310,"malId":45783,"kitsuId":44319,"aniListId":128400,"animeTags":[],"animeGenre":[],"rebroadcast":0,"dub":0,"startPoint":null,"audio":"as1dgl.mp3","video480":null,"video720":"92soq2.webm","correctGuess":true,"incorrectGuess":true},{"animeRomajiName":"Kaijin Kaihatsu-bu no Kuroitsu-san","animeEnglishName":"Miss Kuroitsu from the Monster Development Department","altAnimeNames":["Kaijin Kaihatsu-bu no Kuroitsu-san","Miss Kuroitsu from the Monster Development Department"],"altAnimeNamesAnswers":[],"songArtist":"AXXX1S","songName":"Special Force","songType":1,"songTypeNumber":1,"songDifficulty":26,"animeType":"TV","animeVintage":"Winter 2022","annId":24507,"malId":49385,"kitsuId":44876,"aniListId":136428,"animeTags":[],"animeGenre":[],"rebroadcast":0,"dub":0,"startPoint":null,"audio":"423lc8.mp3","video480":null,"video720":"9f57ei.webm","correctGuess":true,"incorrectGuess":true},{"animeRomajiName":"Cue!","animeEnglishName":"Cue!","altAnimeNames":["Cue!","Cue!"],"altAnimeNamesAnswers":[],"songArtist":"AiRBLUE","songName":"Start Line","songType":1,"songTypeNumber":1,"songDifficulty":28,"animeType":"TV","animeVintage":"Winter 2022","annId":24629,"malId":43735,"kitsuId":44979,"aniListId":125682,"animeTags":[],"animeGenre":[],"rebroadcast":0,"dub":0,"startPoint":null,"audio":"5t83s3.mp3","video480":null,"video720":"okqi5l.webm","correctGuess":true,"incorrectGuess":true},{"animeRomajiName":"Cue!","animeEnglishName":"Cue!","altAnimeNames":["Cue!","Cue!"],"altAnimeNamesAnswers":[],"songArtist":"AiRBLUE","songName":"Tomorrow's Diary","songType":1,"songTypeNumber":2,"songDifficulty":27,"animeType":"TV","animeVintage":"Winter 2022","annId":24629,"malId":43735,"kitsuId":44979,"aniListId":125682,"animeTags":[],"animeGenre":[],"rebroadcast":0,"dub":0,"startPoint":null,"audio":"myppzz.mp3","video480":null,"video720":"3eg1sd.webm","correctGuess":true,"incorrectGuess":true},{"animeRomajiName":"Karakai Jouzu no Takagi-san 3","animeEnglishName":"Teasing Master Takagi-san 3","altAnimeNames":["Karakai Jouzu no Takagi-san 3","Teasing Master Takagi-san 3"],"altAnimeNamesAnswers":[],"songArtist":"Yuiko Ohara","songName":"Massugu","songType":1,"songTypeNumber":1,"songDifficulty":44,"animeType":"TV","animeVintage":"Winter 2022","annId":24696,"malId":49721,"kitsuId":45022,"aniListId":138424,"animeTags":[],"animeGenre":[],"rebroadcast":0,"dub":0,"startPoint":null,"audio":"mbs5nk.mp3","video480":null,"video720":"8oxfgz.webm","correctGuess":true,"incorrectGuess":true},{"animeRomajiName":"Karakai Jouzu no Takagi-san 3","animeEnglishName":"Teasing Master Takagi-san 3","altAnimeNames":["Karakai Jouzu no Takagi-san 3","Teasing Master Takagi-san 3"],"altAnimeNamesAnswers":[],"songArtist":"Yuiko Ohara","songName":"Massugu ~Lalala ver.~","songType":1,"songTypeNumber":2,"songDifficulty":43,"animeType":"TV","animeVintage":"Winter 2022","annId":24696,"malId":49721,"kitsuId":45022,"aniListId":138424,"animeTags":[],"animeGenre":[],"rebroadcast":0,"dub":0,"startPoint":null,"audio":"pfyn0m.mp3","video480":null,"video720":"eslzhp.webm","correctGuess":true,"incorrectGuess":true},{"animeRomajiName":"Genjitsu Shugi Yuusha no Oukoku Saikenki","animeEnglishName":"How a Realist Hero Rebuilt the Kingdom","altAnimeNames":["Genjitsu Shugi Yuusha no Oukoku Saikenki","How a Realist Hero Rebuilt the Kingdom","Genkoku"],"altAnimeNamesAnswers":[],"songArtist":"Inori Minase","songName":"REAL-EYES","songType":1,"songTypeNumber":1,"songDifficulty":35,"animeType":"TV","animeVintage":"Winter 2022","annId":24794,"malId":49930,"kitsuId":45252,"aniListId":139648,"animeTags":[],"animeGenre":[],"rebroadcast":0,"dub":0,"startPoint":null,"audio":"eetvxv.mp3","video480":null,"video720":"kgzbgc.webm","correctGuess":true,"incorrectGuess":true},{"animeRomajiName":"Futsal Boys!!!!!","animeEnglishName":"Futsal Boys!!!!!","altAnimeNames":["Futsal Boys!!!!!","Futsal Boys!!!!!"],"altAnimeNamesAnswers":[],"songArtist":"Takao Sakuma","songName":"BRAVEMAKER","songType":1,"songTypeNumber":1,"songDifficulty":24,"animeType":"TV","animeVintage":"Winter 2022","annId":24044,"malId":40488,"kitsuId":43126,"aniListId":112719,"animeTags":[],"animeGenre":[],"rebroadcast":0,"dub":0,"startPoint":null,"audio":"wdnsaw.mp3","video480":null,"video720":"ljhe3i.webm","correctGuess":true,"incorrectGuess":true},{"animeRomajiName":"Bara-Ou no Souretsu","animeEnglishName":"Requiem of the Rose King","altAnimeNames":["Bara-Ou no Souretsu","Requiem of the Rose King"],"altAnimeNamesAnswers":[],"songArtist":"Makoto Furukawa","songName":"Ware, Bara ni Insu","songType":1,"songTypeNumber":1,"songDifficulty":23,"animeType":"TV","animeVintage":"Winter 2022","annId":24149,"malId":42892,"kitsuId":44208,"aniListId":124060,"animeTags":[],"animeGenre":[],"rebroadcast":0,"dub":0,"startPoint":null,"audio":"7vqngk.mp3","video480":null,"video720":"twfjue.webm","correctGuess":true,"incorrectGuess":true},{"animeRomajiName":"Bara-Ou no Souretsu","animeEnglishName":"Requiem of the Rose King","altAnimeNames":["Bara-Ou no Souretsu","Requiem of the Rose King"],"altAnimeNamesAnswers":[],"songArtist":"Makoto Furukawa","songName":"Ibara Rinbukyoku","songType":1,"songTypeNumber":2,"songDifficulty":24,"animeType":"TV","animeVintage":"Winter 2022","annId":24149,"malId":42892,"kitsuId":44208,"aniListId":124060,"animeTags":[],"animeGenre":[],"rebroadcast":0,"dub":0,"startPoint":null,"audio":"815w49.mp3","video480":null,"video720":"0xlslc.webm","correctGuess":true,"incorrectGuess":true},{"animeRomajiName":"Sasaki to Miyano","animeEnglishName":"Sasaki and Miyano","altAnimeNames":["Sasaki to Miyano","Sasaki and Miyano"],"altAnimeNamesAnswers":[],"songArtist":"Miracle Chimpanzee","songName":"Mabataki","songType":1,"songTypeNumber":1,"songDifficulty":28,"animeType":"TV","animeVintage":"Winter 2022","annId":24453,"malId":44055,"kitsuId":44575,"aniListId":126288,"animeTags":[],"animeGenre":[],"rebroadcast":0,"dub":0,"startPoint":null,"audio":"qpl0gh.mp3","video480":null,"video720":"htivaf.webm","correctGuess":true,"incorrectGuess":true},{"animeRomajiName":"Sabi-iro no Armor: Reimei","animeEnglishName":"Rusted Armors","altAnimeNames":["Sabi-iro no Armor: Reimei","Rusted Armors"],"altAnimeNamesAnswers":[],"songArtist":"Toshiki Masuda, Taiki Satou, Ryuji Sato","songName":"Faith","songType":1,"songTypeNumber":1,"songDifficulty":19,"animeType":"TV","animeVintage":"Winter 2022","annId":24624,"malId":39917,"kitsuId":null,"aniListId":109820,"animeTags":[],"animeGenre":[],"rebroadcast":0,"dub":0,"startPoint":null,"audio":"x76ue3.mp3","video480":null,"video720":"ddtc57.webm","correctGuess":true,"incorrectGuess":true},{"animeRomajiName":"Shingeki no Kyojin: The Final Season","animeEnglishName":"Attack on Titan Final Season","altAnimeNames":["Shingeki no Kyojin: The Final Season","Attack on Titan Final Season"],"altAnimeNamesAnswers":[],"songArtist":"SiM","songName":"The Rumbling","songType":1,"songTypeNumber":1,"songDifficulty":69,"animeType":"TV","animeVintage":"Winter 2022","annId":24648,"malId":48583,"kitsuId":44240,"aniListId":131681,"animeTags":[],"animeGenre":[],"rebroadcast":0,"dub":0,"startPoint":null,"audio":"3m39p3.mp3","video480":null,"video720":"sm619u.webm","correctGuess":true,"incorrectGuess":true},{"animeRomajiName":"Tensai Ouji no Akaji Kokka Saisei Jutsu","animeEnglishName":"The Genius Prince's Guide to Raising a Nation Out of Debt","altAnimeNames":["Tensai Ouji no Akaji Kokka Saisei Jutsu","The Genius Prince's Guide to Raising a Nation Out of Debt"],"altAnimeNamesAnswers":[],"songArtist":"Nagi Yanagi×THE SIXTH LIE","songName":"LEVEL","songType":1,"songTypeNumber":1,"songDifficulty":37,"animeType":"TV","animeVintage":"Winter 2022","annId":23998,"malId":47159,"kitsuId":44020,"aniListId":129190,"animeTags":[],"animeGenre":[],"rebroadcast":0,"dub":0,"startPoint":null,"audio":"tvsyj6.mp3","video480":null,"video720":"rrbnie.webm","correctGuess":true,"incorrectGuess":true},{"animeRomajiName":"Kenja no Deshi o Nanoru Kenja","animeEnglishName":"She Professed Herself Pupil of the Wise Man","altAnimeNames":["Kenja no Deshi o Nanoru Kenja","She Professed Herself Pupil of the Wise Man"],"altAnimeNamesAnswers":[],"songArtist":"Asaka","songName":"Ready Set Go!!","songType":1,"songTypeNumber":1,"songDifficulty":25,"animeType":"TV","animeVintage":"Winter 2022","annId":24191,"malId":42072,"kitsuId":44121,"aniListId":119056,"animeTags":[],"animeGenre":[],"rebroadcast":0,"dub":0,"startPoint":null,"audio":"na7mzx.mp3","video480":null,"video720":"6zjw7k.webm","correctGuess":true,"incorrectGuess":true},{"animeRomajiName":"Fantasy Bishoujo Juniku Ojisan to","animeEnglishName":"Life with an Ordinary Guy Who Reincarnated into a Total Fantasy Knockout","altAnimeNames":["Fantasy Bishoujo Juniku Ojisan to","Life with an Ordinary Guy Who Reincarnated into a Total Fantasy Knockout"],"altAnimeNamesAnswers":[],"songArtist":"Yoshiki Fukuyama","songName":"Akatsuki no Salaryman","songType":1,"songTypeNumber":1,"songDifficulty":36,"animeType":"TV","animeVintage":"Winter 2022","annId":24376,"malId":48997,"kitsuId":44580,"aniListId":134252,"animeTags":[],"animeGenre":[],"rebroadcast":0,"dub":0,"startPoint":null,"audio":"wzyk56.mp3","video480":null,"video720":"i9jmdo.webm","correctGuess":true,"incorrectGuess":true},{"animeRomajiName":"Koroshi Ai","animeEnglishName":"Love of Kill","altAnimeNames":["Koroshi Ai","Love of Kill"],"altAnimeNamesAnswers":[],"songArtist":"Toshiki Masuda","songName":"Midnight Dancer","songType":1,"songTypeNumber":1,"songDifficulty":28,"animeType":"TV","animeVintage":"Winter 2022","annId":24514,"malId":44516,"kitsuId":44226,"aniListId":127050,"animeTags":[],"animeGenre":[],"rebroadcast":0,"dub":0,"startPoint":null,"audio":"qc9o55.mp3","video480":null,"video720":"u7kty9.webm","correctGuess":true,"incorrectGuess":true},{"animeRomajiName":"Arifureta Shokugyou de Sekai Saikyou 2nd Season","animeEnglishName":"Arifureta: From Commonplace to World's Strongest Season 2","altAnimeNames":["Arifureta Shokugyou de Sekai Saikyou 2nd Season","Arifureta: From Commonplace to World's Strongest Season 2"],"altAnimeNamesAnswers":[],"songArtist":"MindaRyn","songName":"Daylight","songType":1,"songTypeNumber":1,"songDifficulty":47,"animeType":"TV","animeVintage":"Winter 2022","annId":24311,"malId":40507,"kitsuId":42611,"aniListId":112323,"animeTags":[],"animeGenre":[],"rebroadcast":0,"dub":0,"startPoint":null,"audio":"g3e8wh.mp3","video480":null,"video720":"6oghqb.webm","correctGuess":true,"incorrectGuess":true},{"animeRomajiName":"Atasha Kawashiri Kodama Da Yo: Dangerous Lifehacker no Tadareta Seikatsu","animeEnglishName":"I'm Kodama Kawashiri","altAnimeNames":["Atasha Kawashiri Kodama Da Yo: Dangerous Lifehacker no Tadareta Seikatsu","I'm Kodama Kawashiri"],"altAnimeNamesAnswers":[],"songArtist":"UROMT","songName":"Nightholic","songType":1,"songTypeNumber":1,"songDifficulty":26,"animeType":"TV","animeVintage":"Winter 2022","annId":24712,"malId":49780,"kitsuId":45149,"aniListId":138912,"animeTags":[],"animeGenre":[],"rebroadcast":0,"dub":0,"startPoint":null,"audio":"iyw1mh.mp3","video480":null,"video720":"9hyca8.webm","correctGuess":true,"incorrectGuess":true},{"animeRomajiName":"Slow Loop","animeEnglishName":"Slow Loop","altAnimeNames":["Slow Loop","Slow Loop"],"altAnimeNamesAnswers":[],"songArtist":"Pokapoka Ion","songName":"Yajirushi→","songType":1,"songTypeNumber":1,"songDifficulty":34,"animeType":"TV","animeVintage":"Winter 2022","annId":23892,"malId":45425,"kitsuId":44381,"aniListId":127549,"animeTags":[],"animeGenre":[],"rebroadcast":0,"dub":0,"startPoint":null,"audio":"8vrzn7.mp3","video480":null,"video720":"ml6bju.webm","correctGuess":true,"incorrectGuess":true},{"animeRomajiName":"Shikkakumon no Saikyou Kenja","animeEnglishName":"The Strongest Sage With the Weakest Crest","altAnimeNames":["Shikkakumon no Saikyou Kenja","The Strongest Sage With the Weakest Crest"],"altAnimeNamesAnswers":[],"songArtist":"fripSide","songName":"Leap of faith","songType":1,"songTypeNumber":1,"songDifficulty":25,"animeType":"TV","animeVintage":"Winter 2022","annId":24000,"malId":47161,"kitsuId":44025,"aniListId":129191,"animeTags":[],"animeGenre":[],"rebroadcast":0,"dub":0,"startPoint":null,"audio":"yahbf6.mp3","video480":null,"video720":"gcw7xc.webm","correctGuess":true,"incorrectGuess":true},{"animeRomajiName":"Vanitas no Karte","animeEnglishName":"The Case Study of Vanitas","altAnimeNames":["Vanitas no Karte","The Case Study of Vanitas"],"altAnimeNamesAnswers":[],"songArtist":"Little Glee Monster","songName":"Your Name","songType":1,"songTypeNumber":1,"songDifficulty":41,"animeType":"TV","animeVintage":"Winter 2022","annId":24741,"malId":49114,"kitsuId":44672,"aniListId":135136,"animeTags":[],"animeGenre":[],"rebroadcast":0,"dub":0,"startPoint":null,"audio":"y6jw2h.mp3","video480":null,"video720":"nyej0e.webm","correctGuess":true,"incorrectGuess":true},{"animeRomajiName":"Ninjala","animeEnglishName":"Ninjala","altAnimeNames":["Ninjala","Ninjala"],"altAnimeNamesAnswers":[],"songArtist":"Kyary Pamyu Pamyu","songName":"Maybe Baby","songType":1,"songTypeNumber":1,"songDifficulty":27,"animeType":"TV","animeVintage":"Winter 2022","annId":24968,"malId":50418,"kitsuId":null,"aniListId":142274,"animeTags":[],"animeGenre":[],"rebroadcast":0,"dub":0,"startPoint":null,"audio":"3q15c7.mp3","video480":null,"video720":"kx0wkt.webm","correctGuess":true,"incorrectGuess":true},{"animeRomajiName":"Ninjala","animeEnglishName":"Ninjala","altAnimeNames":["Ninjala","Ninjala"],"altAnimeNamesAnswers":[],"songArtist":"Kyary Pamyu Pamyu","songName":"Isshin Doutai","songType":1,"songTypeNumber":2,"songDifficulty":28,"animeType":"TV","animeVintage":"Winter 2022","annId":24968,"malId":50418,"kitsuId":null,"aniListId":142274,"animeTags":[],"animeGenre":[],"rebroadcast":0,"dub":0,"startPoint":null,"audio":"geafkt.mp3","video480":null,"video720":"0hh0zo.webm","correctGuess":true,"incorrectGuess":true},{"animeRomajiName":"Ninjala","animeEnglishName":"Ninjala","altAnimeNames":["Ninjala","Ninjala"],"altAnimeNamesAnswers":[],"songArtist":"Kyary Pamyu Pamyu","songName":"OEDOEDO","songType":1,"songTypeNumber":3,"songDifficulty":21,"animeType":"TV","animeVintage":"Winter 2022","annId":24968,"malId":50418,"kitsuId":null,"aniListId":142274,"animeTags":[],"animeGenre":[],"rebroadcast":0,"dub":0,"startPoint":null,"audio":"1wsvdk.mp3","video480":null,"video720":"x384ug.webm","correctGuess":true,"incorrectGuess":true},{"animeRomajiName":"Baby-Hamitang","animeEnglishName":"Baby-Hamitang","altAnimeNames":["Baby-Hamitang","Baby-Hamitang"],"altAnimeNamesAnswers":[],"songArtist":"Baby-Hamitang","songName":"Hello Ni Zd Marha Bon Hola","songType":1,"songTypeNumber":1,"songDifficulty":23,"animeType":"TV","animeVintage":"Winter 2022","annId":25097,"malId":50681,"kitsuId":45824,"aniListId":143416,"animeTags":[],"animeGenre":[],"rebroadcast":0,"dub":0,"startPoint":null,"audio":"rckzba.mp3","video480":null,"video720":"295gvb.webm","correctGuess":true,"incorrectGuess":true},{"animeRomajiName":"Princess Connect! Re:Dive Season 2","animeEnglishName":"Princess Connect! Re:Dive Season 2","altAnimeNames":["Princess Connect! Re:Dive Season 2","Princess Connect! Re:Dive Season 2"],"altAnimeNamesAnswers":[],"songArtist":"M・A・O, Miku Itou, Rika Tachibana","songName":"Lost Princess","songType":1,"songTypeNumber":1,"songDifficulty":59,"animeType":"TV","animeVintage":"Winter 2022","annId":23565,"malId":42670,"kitsuId":43600,"aniListId":122808,"animeTags":[],"animeGenre":[],"rebroadcast":0,"dub":0,"startPoint":null,"audio":"xt8gx4.mp3","video480":"3up9t3.webm","video720":"up6r6m.webm","correctGuess":true,"incorrectGuess":true},{"animeRomajiName":"Sabikui Bisco","animeEnglishName":"Sabikui Bisco","altAnimeNames":["Sabikui Bisco","Sabikui Bisco"],"altAnimeNamesAnswers":[],"songArtist":"JUNNA","songName":"Kaze no Oto sae Kikoenai","songType":1,"songTypeNumber":1,"songDifficulty":35,"animeType":"TV","animeVintage":"Winter 2022","annId":24110,"malId":48414,"kitsuId":44189,"aniListId":130591,"animeTags":[],"animeGenre":[],"rebroadcast":0,"dub":0,"startPoint":null,"audio":"74wcq3.mp3","video480":null,"video720":"4r6gcm.webm","correctGuess":true,"incorrectGuess":true},{"animeRomajiName":"Gensou Sangokushi: Tengen Reishinki","animeEnglishName":"Fantasia Sango: Realm of Legends","altAnimeNames":["Gensou Sangokushi: Tengen Reishinki","Fantasia Sango: Realm of Legends"],"altAnimeNamesAnswers":[],"songArtist":"Machico","songName":"ENISHI","songType":1,"songTypeNumber":1,"songDifficulty":19,"animeType":"TV","animeVintage":"Winter 2022","annId":24576,"malId":49514,"kitsuId":null,"aniListId":137247,"animeTags":[],"animeGenre":[],"rebroadcast":0,"dub":0,"startPoint":null,"audio":"99oyk7.mp3","video480":null,"video720":"tfh09e.webm","correctGuess":true,"incorrectGuess":true},{"animeRomajiName":"Tribe Nine","animeEnglishName":"Tribe Nine","altAnimeNames":["Tribe Nine","Tribe Nine"],"altAnimeNamesAnswers":[],"songArtist":"MIYAVI","songName":"Strike It Out","songType":1,"songTypeNumber":1,"songDifficulty":29,"animeType":"TV","animeVintage":"Winter 2022","annId":24803,"malId":49969,"kitsuId":45271,"aniListId":139804,"animeTags":[],"animeGenre":[],"rebroadcast":0,"dub":0,"startPoint":null,"audio":"2tazjr.mp3","video480":null,"video720":"djvaap.webm","correctGuess":true,"incorrectGuess":true},{"animeRomajiName":"Gal-gaku. II: Lucky Stars","animeEnglishName":"Girl-gaku. II: Lucky Stars","altAnimeNames":["Gal-gaku. II: Lucky Stars","Girl-gaku. II: Lucky Stars"],"altAnimeNamesAnswers":[],"songArtist":"Lucky²","songName":"ichigo ~Ichigo Ichie~","songType":1,"songTypeNumber":1,"songDifficulty":25,"animeType":"TV","animeVintage":"Winter 2022","annId":25017,"malId":50495,"kitsuId":null,"aniListId":142216,"animeTags":[],"animeGenre":[],"rebroadcast":0,"dub":0,"startPoint":null,"audio":"j8bhr2.mp3","video480":null,"video720":"47qq9j.webm","correctGuess":true,"incorrectGuess":true},{"animeRomajiName":"Ryman's Club","animeEnglishName":"Salaryman's Club","altAnimeNames":["Ryman's Club","Salaryman's Club"],"altAnimeNamesAnswers":[],"songArtist":"Novelbright","songName":"The Warrior","songType":1,"songTypeNumber":1,"songDifficulty":22,"animeType":"TV","animeVintage":"Winter 2022","annId":24892,"malId":50185,"kitsuId":45388,"aniListId":140502,"animeTags":[],"animeGenre":[],"rebroadcast":0,"dub":0,"startPoint":null,"audio":"fcd0jk.mp3","video480":null,"video720":"fqj7f4.webm","correctGuess":true,"incorrectGuess":true},{"animeRomajiName":"Eien no 831","animeEnglishName":"Eien no 831","altAnimeNames":["Eien no 831","Eien no 831"],"altAnimeNamesAnswers":[],"songArtist":"KanoeRana","songName":"Kingyobachi","songType":1,"songTypeNumber":1,"songDifficulty":18,"animeType":"Movie","animeVintage":"Winter 2022","annId":24602,"malId":49532,"kitsuId":44955,"aniListId":137378,"animeTags":[],"animeGenre":[],"rebroadcast":0,"dub":0,"startPoint":null,"audio":"vjts82.mp3","video480":null,"video720":"pxnkkq.webm","correctGuess":true,"incorrectGuess":true},{"animeRomajiName":"Delicious Party♡Precure","animeEnglishName":"Delicious Party Pretty Cure","altAnimeNames":["Delicious Party♡Precure","Delicious Party Pretty Cure"],"altAnimeNamesAnswers":[],"songArtist":"Machico","songName":"Cheers! Delicious Party♡Precure","songType":1,"songTypeNumber":1,"songDifficulty":44,"animeType":"TV","animeVintage":"Winter 2022","annId":24994,"malId":50281,"kitsuId":45733,"aniListId":142080,"animeTags":[],"animeGenre":[],"rebroadcast":0,"dub":0,"startPoint":null,"audio":"2g605h.mp3","video480":null,"video720":"1m9tws.webm","correctGuess":true,"incorrectGuess":true},{"animeRomajiName":"Kotarou wa Hitorigurashi","animeEnglishName":"Kotaro Lives Alone","altAnimeNames":["Kotarou wa Hitorigurashi","Kotaro Lives Alone"],"altAnimeNamesAnswers":[],"songArtist":"KOCHO","songName":"Hoshi no Runway","songType":1,"songTypeNumber":1,"songDifficulty":15,"animeType":"ONA","animeVintage":"Winter 2022","annId":24767,"malId":49909,"kitsuId":45245,"aniListId":139589,"animeTags":[],"animeGenre":[],"rebroadcast":0,"dub":0,"startPoint":null,"audio":"f6w92p.mp3","video480":null,"video720":"im2r7z.webm","correctGuess":true,"incorrectGuess":true},{"animeRomajiName":"Kotarou wa Hitorigurashi","animeEnglishName":"Kotaro Lives Alone","altAnimeNames":["Kotarou wa Hitorigurashi","Kotaro Lives Alone"],"altAnimeNamesAnswers":[],"songArtist":"Enri Yamada","songName":"Tonosaman no Uta","songType":1,"songTypeNumber":2,"songDifficulty":19,"animeType":"ONA","animeVintage":"Winter 2022","annId":24767,"malId":49909,"kitsuId":45245,"aniListId":139589,"animeTags":[],"animeGenre":[],"rebroadcast":0,"dub":0,"startPoint":null,"audio":"eqfm1w.mp3","video480":null,"video720":"qzozte.webm","correctGuess":true,"incorrectGuess":true},{"animeRomajiName":"Ginga Eiyuu Densetsu: Die Neue These - Gekitotsu","animeEnglishName":"Legend of the Galactic Heroes: Die Neue These - Collision","altAnimeNames":["Ginga Eiyuu Densetsu: Die Neue These - Gekitotsu","Legend of the Galactic Heroes: Die Neue These - Collision"],"altAnimeNamesAnswers":[],"songArtist":"SennaRin","songName":"dust","songType":1,"songTypeNumber":1,"songDifficulty":25,"animeType":"Movie","animeVintage":"Winter 2022","annId":24830,"malId":42886,"kitsuId":44169,"aniListId":124032,"animeTags":[],"animeGenre":[],"rebroadcast":0,"dub":0,"startPoint":null,"audio":"87brjl.mp3","video480":null,"video720":"ets19v.webm","correctGuess":true,"incorrectGuess":true},{"animeRomajiName":"Thermae Romae Novae","animeEnglishName":"Thermae Romae Novae","altAnimeNames":["Thermae Romae Novae","Thermae Romae Novae"],"altAnimeNamesAnswers":[],"songArtist":"Paolo Andrea Di Pietro","songName":"Tougyuushi no Uta ~Onsen Manner no Aria~","songType":1,"songTypeNumber":1,"songDifficulty":26,"animeType":"ONA","animeVintage":"Winter 2022","annId":24455,"malId":43693,"kitsuId":43702,"aniListId":125447,"animeTags":[],"animeGenre":[],"rebroadcast":0,"dub":0,"startPoint":null,"audio":"tm7je0.mp3","video480":null,"video720":"hdgd8o.webm","correctGuess":true,"incorrectGuess":true},{"animeRomajiName":"Strike the Blood Final","animeEnglishName":"Strike the Blood Final","altAnimeNames":["Strike the Blood Final","Strike the Blood Final"],"altAnimeNamesAnswers":[],"songArtist":"Kishida Kyoudan &THE Akeboshi Rockets","songName":"Akatsuki no Kaleido Blood","songType":1,"songTypeNumber":1,"songDifficulty":39,"animeType":"OVA","animeVintage":"Winter 2022","annId":24484,"malId":49316,"kitsuId":null,"aniListId":136226,"animeTags":[],"animeGenre":[],"rebroadcast":0,"dub":0,"startPoint":null,"audio":"yn0k2c.mp3","video480":null,"video720":"vmds9t.webm","correctGuess":true,"incorrectGuess":true},{"animeRomajiName":"I Love Me","animeEnglishName":"I Love Me","altAnimeNames":["I Love Me","I Love Me"],"altAnimeNamesAnswers":[],"songArtist":"Humbert Humbert","songName":"I Love Me no Theme","songType":1,"songTypeNumber":1,"songDifficulty":18,"animeType":"TV","animeVintage":"Winter 2022","annId":25405,"malId":51154,"kitsuId":null,"aniListId":154041,"animeTags":[],"animeGenre":[],"rebroadcast":0,"dub":0,"startPoint":null,"audio":"3iknhv.mp3","video480":null,"video720":"bqrl6o.webm","correctGuess":true,"incorrectGuess":true},{"animeRomajiName":"Miko Note Episode 0: Zenjitsudan","animeEnglishName":"Miko Note Episode 0: Zenjitsudan","altAnimeNames":["Miko Note Episode 0: Zenjitsudan","Miko Note Episode 0: Zenjitsudan"],"altAnimeNamesAnswers":[],"songArtist":"Shuka Saitou, Lynn, Yuu Sasahara","songName":"Irreplaceable Note","songType":1,"songTypeNumber":1,"songDifficulty":20,"animeType":"ONA","animeVintage":"Winter 2022","annId":25502,"malId":51238,"kitsuId":null,"aniListId":170443,"animeTags":[],"animeGenre":[],"rebroadcast":0,"dub":0,"startPoint":null,"audio":"3vxxdx.mp3","video480":null,"video720":"w5mh7d.webm","correctGuess":true,"incorrectGuess":true},{"animeRomajiName":"Echigo Bakufu","animeEnglishName":"Echigo Bakufu","altAnimeNames":["Echigo Bakufu","Echigo Bakufu"],"altAnimeNamesAnswers":[],"songArtist":"Kaito Okuzaki","songName":"Noutenki","songType":1,"songTypeNumber":1,"songDifficulty":15,"animeType":"TV","animeVintage":"Winter 2022","annId":25510,"malId":51336,"kitsuId":null,"aniListId":170823,"animeTags":[],"animeGenre":[],"rebroadcast":0,"dub":0,"startPoint":null,"audio":"15bpcp.mp3","video480":null,"video720":"903soj.webm","correctGuess":true,"incorrectGuess":true},{"animeRomajiName":"BanG Dream! Poppin'Dream!","animeEnglishName":"BanG Dream! Poppin'Dream!","altAnimeNames":["BanG Dream! Poppin'Dream!","BanG Dream! Poppin'Dream!"],"altAnimeNamesAnswers":[],"songArtist":"Poppin'Party","songName":"Poppin'Dream!","songType":1,"songTypeNumber":1,"songDifficulty":39,"animeType":"Movie","animeVintage":"Winter 2022","annId":23929,"malId":41782,"kitsuId":44525,"aniListId":117765,"animeTags":[],"animeGenre":[],"rebroadcast":0,"dub":0,"startPoint":null,"audio":"9gaqnv.mp3","video480":null,"video720":"ycq2b1.webm","correctGuess":true,"incorrectGuess":true},{"animeRomajiName":"Ryuukyuu Timeline 2: Tedako no Machi Tanbou","animeEnglishName":"Ryuukyuu Timeline 2: Tedako no Machi Tanbou","altAnimeNames":["Ryuukyuu Timeline 2: Tedako no Machi Tanbou","Ryuukyuu Timeline 2: Tedako no Machi Tanbou"],"altAnimeNamesAnswers":[],"songArtist":"Harumi Ooki","songName":"Tropical Sunset","songType":1,"songTypeNumber":1,"songDifficulty":20,"animeType":"ONA","animeVintage":"Winter 2022","annId":26819,"malId":53861,"kitsuId":46952,"aniListId":162745,"animeTags":[],"animeGenre":[],"rebroadcast":0,"dub":0,"startPoint":null,"audio":"vqcmq3.mp3","video480":null,"video720":"n3qknb.webm","correctGuess":true,"incorrectGuess":true}]